[{"start": 6, "end": 18, "inSample1": 1, "inSample2": 1}, {"start": 4, "end": 55, "inSample1": 1, "inSample2": 1}, {"start": 27, "end": 50, "inSample1": 1, "inSample2": 1}, {"start": 1, "end": 31, "inSample1": 1, "inSample2": 1}, {"start": 17, "end": 58, "inSample1": 1, "inSample2": 1}, {"start": 42, "end": 57, "inSample1": 1, "inSample2": 1}, {"start": 35, "end": 51, "inSample1": 1, "inSample2": 1}, {"start": 17, "end": 21, "inSample1": 1, "inSample2": 1}, {"start": 29, "end": 50, "inSample1": 1, "inSample2": 1}, {"start": 9, "end": 26, "inSample1": 1, "inSample2": 1}, {"start": 5, "end": 37, "inSample1": 1, "inSample2": 1}, {"start": 34, "end": 58, "inSample1": 1, "inSample2": 1}, {"start": 13, "end": 35, "inSample1": 1, "inSample2": 1}, {"start": 3, "end": 6, "inSample1": 1, "inSample2": 1}, {"start": 5, "end": 12, "inSample1": 1, "inSample2": 1}, {"start": 8, "end": 11, "inSample1": 1, "inSample2": 1}, {"start": 3, "end": 33, "inSample1": 1, "inSample2": 1}, {"start": 4, "end": 32, "inSample1": 1, "inSample2": 1}, {"start": 10, "end": 20, "inSample1": 1, "inSample2": 1}, {"start": 17, "end": 44, "inSample1": 1, "inSample2": 1}, {"start": 18, "end": 21, "inSample1": 1, "inSample2": 1}, {"start": 1, "end": 35, "inSample1": 1, "inSample2": 1}, {"start": 7, "end": 21, "inSample1": 1, "inSample2": 1}, {"start": 25, "end": 36, "inSample1": 1, "inSample2": 1}, {"start": 42, "end": 52, "inSample1": 1, "inSample2": 1}, {"start": 9, "end": 58, "inSample1": 1, "inSample2": 1}, {"start": 14, "end": 17, "inSample1": 1, "inSample2": 1}, {"start": 46, "end": 52, "inSample1": 1, "inSample2": 1}, {"start": 31, "end": 33, "inSample1": 1, "inSample2": 1}, {"start": 14, "end": 26, "inSample1": 1, "inSample2": 1}, {"start": 5, "end": 23, "inSample1": 1, "inSample2": 1}, {"start": 9, "end": 21, "inSample1": 1, "inSample2": 1}, {"start": 14, "end": 44, "inSample1": 1, "inSample2": 1}, {"start": 1, "end": 10, "inSample1": 1, "inSample2": 1}, {"start": 13, "end": 21, "inSample1": 1, "inSample2": 1}, {"start": 34, "end": 53, "inSample1": 1, "inSample2": 1}, {"start": 27, "end": 47, "inSample1": 1, "inSample2": 1}, {"start": 0, "end": 30, "inSample1": 1, "inSample2": 1}, {"start": 25, "end": 29, "inSample1": 1, "inSample2": 1}, {"start": 43, "end": 55, "inSample1": 1, "inSample2": 1}, {"start": 20, "end": 35, "inSample1": 1, "inSample2": 1}, {"start": 4, "end": 18, "inSample1": 1, "inSample2": 1}, {"start": 21, "end": 34, "inSample1": 1, "inSample2": 1}, {"start": 9, "end": 14, "inSample1": 1, "inSample2": 1}, {"start": 29, "end": 47, "inSample1": 1, "inSample2": 1}, {"start": 4, "end": 27, "inSample1": 1, "inSample2": 1}, {"start": 1, "end": 3, "inSample1": 1, "inSample2": 1}, {"start": 7, "end": 53, "inSample1": 1, "inSample2": 1}, {"start": 21, "end": 52, "inSample1": 1, "inSample2": 1}, {"start": 4, "end": 45, "inSample1": 1, "inSample2": 1}, {"start": 19, "end": 27, "inSample1": 1, "inSample2": 1}, {"start": 8, "end": 27, "inSample1": 1, "inSample2": 1}, {"start": 37, "end": 51, "inSample1": 1, "inSample2": 1}, {"start": 17, "end": 48, "inSample1": 1, "inSample2": 1}, {"start": 9, "end": 44, "inSample1": 1, "inSample2": 1}, {"start": 4, "end": 11, "inSample1": 1, "inSample2": 1}, {"start": 39, "end": 41, "inSample1": 1, "inSample2": 1}, {"start": 43, "end": 57, "inSample1": 1, "inSample2": 1}, {"start": 48, "end": 53, "inSample1": 1, "inSample2": 1}, {"start": 12, "end": 33, "inSample1": 1, "inSample2": 1}, {"start": 23, "end": 33, "inSample1": 1, "inSample2": 1}, {"start": 4, "end": 29, "inSample1": 1, "inSample2": 1}, {"start": 1, "end": 5, "inSample1": 1, "inSample2": 1}, {"start": 4, "end": 38, "inSample1": 1, "inSample2": 1}, {"start": 7, "end": 55, "inSample1": 1, "inSample2": 1}, {"start": 21, "end": 54, "inSample1": 1, "inSample2": 1}, {"start": 27, "end": 33, "inSample1": 1, "inSample2": 1}, {"start": 8, "end": 29, "inSample1": 1, "inSample2": 1}, {"start": 19, "end": 29, "inSample1": 1, "inSample2": 1}, {"start": 34, "end": 48, "inSample1": 1, "inSample2": 1}, {"start": 11, "end": 25, "inSample1": 1, "inSample2": 1}, {"start": 1, "end": 23, "inSample1": 1, "inSample2": 1}, {"start": 33, "end": 37, "inSample1": 1, "inSample2": 1}, {"start": 1, "end": 32, "inSample1": 1, "inSample2": 1}, {"start": 8, "end": 56, "inSample1": 1, "inSample2": 1}, {"start": 29, "end": 33, "inSample1": 1, "inSample2": 1}, {"start": 26, "end": 43, "inSample1": 1, "inSample2": 1}, {"start": 4, "end": 22, "inSample1": 1, "inSample2": 1}, {"start": 44, "end": 58, "inSample1": 1, "inSample2": 1}, {"start": 18, "end": 57, "inSample1": 1, "inSample2": 1}, {"start": 8, "end": 22, "inSample1": 1, "inSample2": 1}, {"start": 19, "end": 22, "inSample1": 1, "inSample2": 1}, {"start": 53, "end": 54, "inSample1": 1, "inSample2": 1}, {"start": 17, "end": 34, "inSample1": 1, "inSample2": 1}, {"start": 8, "end": 31, "inSample1": 1, "inSample2": 1}, {"start": 0, "end": 27, "inSample1": 1, "inSample2": 1}, {"start": 2, "end": 24, "inSample1": 1, "inSample2": 1}, {"start": 8, "end": 40, "inSample1": 1, "inSample2": 1}, {"start": 5, "end": 41, "inSample1": 1, "inSample2": 1}, {"start": 0, "end": 36, "inSample1": 1, "inSample2": 1}, {"start": 15, "end": 27, "inSample1": 1, "inSample2": 1}, {"start": 4, "end": 6, "inSample1": 1, "inSample2": 1}, {"start": 12, "end": 19, "inSample1": 1, "inSample2": 1}, {"start": 14, "end": 16, "inSample1": 1, "inSample2": 1}, {"start": 15, "end": 36, "inSample1": 1, "inSample2": 1}, {"start": 1, "end": 55, "inSample1": 1, "inSample2": 1}, {"start": 26, "end": 54, "inSample1": 1, "inSample2": 1}, {"start": 0, "end": 11, "inSample1": 1, "inSample2": 1}, {"start": 2, "end": 8, "inSample1": 1, "inSample2": 1}, {"start": 1, "end": 18, "inSample1": 1, "inSample2": 1}, {"start": 54, "end": 55, "inSample1": 1, "inSample2": 1}, {"start": 0, "end": 29, "inSample1": 1, "inSample2": 1}, {"start": 28, "end": 45, "inSample1": 1, "inSample2": 1}, {"start": 14, "end": 55, "inSample1": 1, "inSample2": 1}, {"start": 15, "end": 29, "inSample1": 1, "inSample2": 1}, {"start": 14, "end": 18, "inSample1": 1, "inSample2": 1}, {"start": 3, "end": 18, "inSample1": 1, "inSample2": 1}, {"start": 7, "end": 43, "inSample1": 1, "inSample2": 1}, {"start": 21, "end": 42, "inSample1": 1, "inSample2": 1}, {"start": 18, "end": 43, "inSample1": 1, "inSample2": 1}, {"start": 4, "end": 35, "inSample1": 1, "inSample2": 1}, {"start": 1, "end": 11, "inSample1": 1, "inSample2": 1}, {"start": 11, "end": 22, "inSample1": 1, "inSample2": 1}, {"start": 14, "end": 48, "inSample1": 1, "inSample2": 1}, {"start": 0, "end": 31, "inSample1": 1, "inSample2": 1}, {"start": 0, "end": 40, "inSample1": 1, "inSample2": 1}, {"start": 15, "end": 31, "inSample1": 1, "inSample2": 1}, {"start": 4, "end": 10, "inSample1": 1, "inSample2": 1}, {"start": 1, "end": 41, "inSample1": 1, "inSample2": 1}, {"start": 21, "end": 26, "inSample1": 1, "inSample2": 1}, {"start": 21, "end": 35, "inSample1": 1, "inSample2": 1}, {"start": 7, "end": 54, "inSample1": 1, "inSample2": 1}, {"start": 11, "end": 15, "inSample1": 1, "inSample2": 1}, {"start": 19, "end": 37, "inSample1": 1, "inSample2": 1}, {"start": 8, "end": 37, "inSample1": 1, "inSample2": 1}, {"start": 11, "end": 33, "inSample1": 1, "inSample2": 1}, {"start": 3, "end": 4, "inSample1": 1, "inSample2": 1}, {"start": 9, "end": 54, "inSample1": 1, "inSample2": 1}, {"start": 44, "end": 48, "inSample1": 1, "inSample2": 1}, {"start": 19, "end": 30, "inSample1": 1, "inSample2": 1}, {"start": 8, "end": 30, "inSample1": 1, "inSample2": 1}, {"start": 21, "end": 58, "inSample1": 1, "inSample2": 1}, {"start": 5, "end": 49, "inSample1": 1, "inSample2": 1}, {"start": 6, "end": 14, "inSample1": 1, "inSample2": 1}, {"start": 1, "end": 27, "inSample1": 1, "inSample2": 1}, {"start": 4, "end": 5, "inSample1": 1, "inSample2": 1}, {"start": 1, "end": 45, "inSample1": 1, "inSample2": 1}, {"start": 0, "end": 56, "inSample1": 1, "inSample2": 1}, {"start": 8, "end": 23, "inSample1": 1, "inSample2": 1}, {"start": 19, "end": 23, "inSample1": 1, "inSample2": 1}, {"start": 11, "end": 19, "inSample1": 1, "inSample2": 1}, {"start": 28, "end": 35, "inSample1": 1, "inSample2": 1}, {"start": 5, "end": 51, "inSample1": 1, "inSample2": 1}, {"start": 1, "end": 29, "inSample1": 1, "inSample2": 1}, {"start": 24, "end": 40, "inSample1": 1, "inSample2": 1}, {"start": 1, "end": 38, "inSample1": 1, "inSample2": 1}, {"start": 4, "end": 16, "inSample1": 1, "inSample2": 1}, {"start": 35, "end": 49, "inSample1": 1, "inSample2": 1}, {"start": 18, "end": 42, "inSample1": 1, "inSample2": 1}, {"start": 22, "end": 33, "inSample1": 1, "inSample2": 1}, {"start": 49, "end": 51, "inSample1": 1, "inSample2": 1}, {"start": 20, "end": 45, "inSample1": 1, "inSample2": 1}, {"start": 21, "end": 53, "inSample1": 1, "inSample2": 1}, {"start": 1, "end": 22, "inSample1": 1, "inSample2": 1}]